EventMaster/__init__.py
EventMaster-160716a0.dist-info/DESCRIPTION.rst
EventMaster-160716a0.dist-info/METADATA
EventMaster-160716a0.dist-info/RECORD
EventMaster-160716a0.dist-info/WHEEL
EventMaster-160716a0.dist-info/metadata.json
EventMaster-160716a0.dist-info/top_level.txt
