Metadata-Version: 2.0
Name: EventMaster
Version: 160716a0
Summary: Unofficial Python Library for connecting to, reading from and controlling a Barco E2, S3 or other EventMaster Switcher
Home-page: http://github.com/kyelewisstgc/EventMaster-Python
Author: Kye Lewis
Author-email: klewis@stagingconnections.com
License: UNKNOWN
Download-URL: https://github.com/kyelewisstgc/EventMaster-Python/tarball/0.1
Keywords: control barco E2 S3 eventmaster
Platform: UNKNOWN
Classifier: Development Status :: 3 - Alpha
Classifier: Intended Audience :: Developers
Classifier: Programming Language :: Python :: 2.7
Classifier: Programming Language :: Python :: 3.3
